{"_type":"export","__export_format":4,"__export_date":"2023-10-26T20:56:19.097Z","__export_source":"insomnia.desktop.app:v2023.5.8","resources":[{"_id":"req_735a527cb4b344ffaf6646fcb35d1cf1","parentId":"fld_e68e385f3dca4d43b73d015129b40987","modified":1698338944229,"created":1698331125584,"url":"http://localhost:8080/api/user/1","name":"GetById","description":"","method":"GET","body":{},"parameters":[],"headers":[{"name":"User-Agent","value":"insomnia/2023.5.8"}],"authentication":{},"metaSortKey":-1698332088435,"isPrivate":false,"settingStoreCookies":true,"settingSendCookies":true,"settingDisableRenderRequestBody":false,"settingEncodeUrl":true,"settingRebuildPath":true,"settingFollowRedirects":"global","_type":"request"},{"_id":"fld_e68e385f3dca4d43b73d015129b40987","parentId":"wrk_4557a15a99324cbaa64ee90e96824b6f","modified":1698332115321,"created":1698332080989,"name":"User","description":"","environment":{},"environmentPropertyOrder":null,"metaSortKey":-1698332080989,"_type":"request_group"},{"_id":"wrk_4557a15a99324cbaa64ee90e96824b6f","parentId":null,"modified":1698326969890,"created":1698326969890,"name":"TaxisLibres","description":"","scope":"collection","_type":"workspace"},{"_id":"req_8b8e9f8a975e4edc9280303e779b288a","parentId":"fld_e68e385f3dca4d43b73d015129b40987","modified":1698348633048,"created":1698327667769,"url":"http://localhost:8080/api/user","name":"Create","description":"","method":"POST","body":{"mimeType":"application/json","text":"{\n\t\"name\": \"test\",\n\t\"email\": \"asdf@gmail.com\",\n\t\"age\": 24\n}"},"parameters":[],"headers":[{"name":"Content-Type","value":"application/json"},{"name":"User-Agent","value":"insomnia/2023.5.8"}],"authentication":{},"metaSortKey":-1698332088335,"isPrivate":false,"settingStoreCookies":true,"settingSendCookies":true,"settingDisableRenderRequestBody":false,"settingEncodeUrl":true,"settingRebuildPath":true,"settingFollowRedirects":"global","_type":"request"},{"_id":"req_7acd3bb1c3024aa1ba6b85e97dd72994","parentId":"fld_e68e385f3dca4d43b73d015129b40987","modified":1698348690764,"created":1698326972316,"url":"http://localhost:8080/api/user?email=ingrejhon@gmail.com","name":"GetByEmail","description":"","method":"GET","body":{},"parameters":[],"headers":[{"name":"User-Agent","value":"insomnia/2023.5.8"}],"authentication":{},"metaSortKey":-1698332088235,"isPrivate":false,"settingStoreCookies":true,"settingSendCookies":true,"settingDisableRenderRequestBody":false,"settingEncodeUrl":true,"settingRebuildPath":true,"settingFollowRedirects":"global","_type":"request"},{"_id":"req_ec097bac45a14caf9822420502ec9a7c","parentId":"fld_0f900de5c83b40dcb927b3f1ba70ec0f","modified":1698351971745,"created":1698351913489,"url":"http://localhost:8080/api/bill/3","name":"Update","description":"","method":"PUT","body":{"mimeType":"application/json","text":"{\n    \"totalAmount\": 42.56,\n    \"description\": \"test\",\n    \"idUser\": 1\n}"},"parameters":[],"headers":[{"name":"Content-Type","value":"application/json"},{"name":"User-Agent","value":"insomnia/2023.5.8"}],"authentication":{},"metaSortKey":-1698351913489,"isPrivate":false,"settingStoreCookies":true,"settingSendCookies":true,"settingDisableRenderRequestBody":false,"settingEncodeUrl":true,"settingRebuildPath":true,"settingFollowRedirects":"global","_type":"request"},{"_id":"fld_0f900de5c83b40dcb927b3f1ba70ec0f","parentId":"wrk_4557a15a99324cbaa64ee90e96824b6f","modified":1698332109297,"created":1698332071268,"name":"Bill","description":"","environment":{},"environmentPropertyOrder":null,"metaSortKey":-1698332071268,"_type":"request_group"},{"_id":"req_0ed9e6cda8d140d7bffa5c82676c4bfc","parentId":"fld_0f900de5c83b40dcb927b3f1ba70ec0f","modified":1698348872843,"created":1698332117966,"url":"http://localhost:8080/api/bill/2","name":"GetById","description":"","method":"GET","body":{},"parameters":[],"headers":[{"name":"User-Agent","value":"insomnia/2023.5.8"}],"authentication":{},"metaSortKey":-1698332117966,"isPrivate":false,"settingStoreCookies":true,"settingSendCookies":true,"settingDisableRenderRequestBody":false,"settingEncodeUrl":true,"settingRebuildPath":true,"settingFollowRedirects":"global","_type":"request"},{"_id":"req_68cbfece51b743a590929dd19f1f05f4","parentId":"fld_0f900de5c83b40dcb927b3f1ba70ec0f","modified":1698352677949,"created":1698352567291,"url":"http://localhost:8080/api/bill/20","name":"Delete","description":"","method":"DELETE","body":{},"parameters":[],"headers":[{"name":"User-Agent","value":"insomnia/2023.5.8"}],"authentication":{},"metaSortKey":-1698332110583.25,"isPrivate":false,"settingStoreCookies":true,"settingSendCookies":true,"settingDisableRenderRequestBody":false,"settingEncodeUrl":true,"settingRebuildPath":true,"settingFollowRedirects":"global","_type":"request"},{"_id":"req_ef0cb95bd0f34eb5aeca3be7b18b89d4","parentId":"fld_0f900de5c83b40dcb927b3f1ba70ec0f","modified":1698350726503,"created":1698348880285,"url":"http://localhost:8080/api/bill","name":"Create","description":"","method":"POST","body":{"mimeType":"application/json","text":"{\n    \"totalAmount\": 42.56,\n    \"description\": \"test\",\n    \"idUser\": 1\n}"},"parameters":[],"headers":[{"name":"Content-Type","value":"application/json"},{"name":"User-Agent","value":"insomnia/2023.5.8"}],"authentication":{},"metaSortKey":-1698332103200.5,"isPrivate":false,"settingStoreCookies":true,"settingSendCookies":true,"settingDisableRenderRequestBody":false,"settingEncodeUrl":true,"settingRebuildPath":true,"settingFollowRedirects":"global","_type":"request"},{"_id":"env_053e58f301317219f6b38dbc213c702ef41d5a0d","parentId":"wrk_4557a15a99324cbaa64ee90e96824b6f","modified":1698326969896,"created":1698326969896,"name":"Base Environment","data":{},"dataPropertyOrder":null,"color":null,"isPrivate":false,"metaSortKey":1698326969896,"_type":"environment"},{"_id":"jar_053e58f301317219f6b38dbc213c702ef41d5a0d","parentId":"wrk_4557a15a99324cbaa64ee90e96824b6f","modified":1698326969900,"created":1698326969900,"name":"Default Jar","cookies":[],"_type":"cookie_jar"}]}